{
  "keys": [
    {
      "key": "sk-live-V4dyXhcHcQCFuxnLYWKmBM2jzKxDilFMl4BklW67",
      "rateLimitResetTimestamp": 0,
      "isAvailable": true,
      "usageCount": 31,
      "monthlyUsage": 31,
      "lastMonthReset": "2025-05",
      "lastErrorTimestamp": 0
    },
    {
      "key": "sk-live-kQSxsVhWZyIk8sGy2gzXGBvi97RETSP88OOG2qt3",
      "rateLimitResetTimestamp": 0,
      "isAvailable": true,
      "usageCount": 0,
      "monthlyUsage": 0,
      "lastMonthReset": "2025-05",
      "lastErrorTimestamp": 0
    },
    {
      "key": "sk-live-QtygcAU1VLXuNtIHRAVNWnLrtoTpL0yctd2DEko5",
      "rateLimitResetTimestamp": 0,
      "isAvailable": true,
      "usageCount": 0,
      "monthlyUsage": 0,
      "lastMonthReset": "2025-05",
      "lastErrorTimestamp": 0
    },
    {
      "key": "sk-live-bi47a6KsAGkHsFAguG0sKBNzCf8VbTVFweOy1eFE",
      "rateLimitResetTimestamp": 0,
      "isAvailable": true,
      "usageCount": 0,
      "monthlyUsage": 0,
      "lastMonthReset": "2025-05",
      "lastErrorTimestamp": 0
    },
    {
      "key": "sk-live-uZup2KEHVqDo2zyAunRH0zp9aaRNpyGgxKU7GApI",
      "rateLimitResetTimestamp": 0,
      "isAvailable": true,
      "usageCount": 0,
      "monthlyUsage": 0,
      "lastMonthReset": "2025-05",
      "lastErrorTimestamp": 0
    },
    {
      "key": "sk-live-rB1W61qZPLlzufRlnRfS937jYQBEmM8D4TUPdpFh",
      "rateLimitResetTimestamp": 0,
      "isAvailable": true,
      "usageCount": 0,
      "monthlyUsage": 0,
      "lastMonthReset": "2025-05",
      "lastErrorTimestamp": 0
    },
    {
      "key": "sk-live-1jzFVqgbxWnQCwRgG9NynigeR72HtkbioKch1VaD",
      "rateLimitResetTimestamp": 0,
      "isAvailable": true,
      "usageCount": 0,
      "monthlyUsage": 0,
      "lastMonthReset": "2025-05",
      "lastErrorTimestamp": 0
    },
    {
      "key": "sk-live-2SrhjLseRYGxjv8JzfGFZ3D4ZyGOqZatL8ADODKL",
      "rateLimitResetTimestamp": 0,
      "isAvailable": true,
      "usageCount": 0,
      "monthlyUsage": 0,
      "lastMonthReset": "2025-05",
      "lastErrorTimestamp": 0
    },
    {
      "key": "sk-live-2cEMmBrNbaIP1v3OjVNwNMbRnO49hvCeOayo5jAA",
      "rateLimitResetTimestamp": 0,
      "isAvailable": true,
      "usageCount": 0,
      "monthlyUsage": 0,
      "lastMonthReset": "2025-05",
      "lastErrorTimestamp": 0
    },
    {
      "key": "sk-live-jtOlHh18hooTAJQmcLUz4mngn9gxSvY4uRyVUpGJ",
      "rateLimitResetTimestamp": 0,
      "isAvailable": true,
      "usageCount": 0,
      "monthlyUsage": 0,
      "lastMonthReset": "2025-05",
      "lastErrorTimestamp": 0
    }
  ]
}